{
  "users": [
    {
      "id": 1,
      "email": "nguyenvana@gmail.com",
      "password": "1234567",
      "fullName": "Nguyễn Văn A",
      "sex": "2",
      "age": "26"
    },
    {
      "id": 2,
      "email": "tranthib@gmail.com",
      "password": "1234567",
      "fullName": "Trần Thị B",
      "sex": "2",
      "age": "30"
    }
  ],
  "schedules": [
    {
      "id": 555,
      "date": "2023-12-01",
      "reminds": [
        {
          "id": 1,
          "time": "12:00",
          "text": "Meeting at 10am",
          "scheduleId": 555
        }
      ],
      "userEmail": "nguyenvana@gmail.com"
    },
    {
      "id": 666,
      "date": "2023-12-12",
      "reminds": [
        {
          "id": 2,
          "time": "12:00",
          "text": "Lunch with colleagues",
          "scheduleId": 666
        },
        {
          "id": 3,
          "time": "12:00",
          "text": "Shopping",
          "scheduleId": 666
        }
      ],
      "userEmail": "nguyenvana@gmail.com"
    },
    {
      "id": 777,
      "date": "2023-12-13",
      "reminds": [
        {
          "id": 4,
          "time": "12:00",
          "text": "Gym at 5pm",
          "scheduleId": 777
        }
      ],
      "userEmail": "tranthib@gmail.com"
    },
    {
      "id": 888,
      "date": "2023-12-14",
      "diaries": [
        {
          "id": 5,
          "sick": "Cao huyết áp",
          "symptoms": "Nhức đầu",
          "description": "Đau hoài",
          "scheduleId": 888
        }
      ],
      "userEmail": "nguyenvana@gmail.com"
    }
  ],
  "sicks": [
    {
      "id": "1",
      "name": "Đái tháo đường"
    },
    {
      "id": "2",
      "name": "Tim"
    }
  ],
  "savedSicks": [
    {
      "id": 1,
      "usersId": 1,
      "sicksId": "1"
    },
    {
      "usersId": 1,
      "sicksId": "2",
      "id": 2
    }
  ]
}